rmw_security_common/_dummy.cpython-310-x86_64-linux-gnu.so
ros_rmw_security_common-7.8.2.data/data/include/rmw_security_common/rmw_security_common/security.hpp
ros_rmw_security_common-7.8.2.data/data/include/rmw_security_common/rmw_security_common/visibility_control.h
ros_rmw_security_common-7.8.2.data/data/lib/librmw_security_common.so
ros_rmw_security_common-7.8.2.data/data/share/ament_index/resource_index/package_run_dependencies/rmw_security_common
ros_rmw_security_common-7.8.2.data/data/share/ament_index/resource_index/packages/rmw_security_common
ros_rmw_security_common-7.8.2.data/data/share/ament_index/resource_index/parent_prefix_path/rmw_security_common
ros_rmw_security_common-7.8.2.data/data/share/rmw_security_common/local_setup.bash
ros_rmw_security_common-7.8.2.data/data/share/rmw_security_common/local_setup.dsv
ros_rmw_security_common-7.8.2.data/data/share/rmw_security_common/local_setup.sh
ros_rmw_security_common-7.8.2.data/data/share/rmw_security_common/local_setup.zsh
ros_rmw_security_common-7.8.2.data/data/share/rmw_security_common/package.dsv
ros_rmw_security_common-7.8.2.data/data/share/rmw_security_common/package.xml
ros_rmw_security_common-7.8.2.data/data/share/rmw_security_common/cmake/ament_cmake_export_dependencies-extras.cmake
ros_rmw_security_common-7.8.2.data/data/share/rmw_security_common/cmake/ament_cmake_export_include_directories-extras.cmake
ros_rmw_security_common-7.8.2.data/data/share/rmw_security_common/cmake/ament_cmake_export_libraries-extras.cmake
ros_rmw_security_common-7.8.2.data/data/share/rmw_security_common/cmake/ament_cmake_export_targets-extras.cmake
ros_rmw_security_common-7.8.2.data/data/share/rmw_security_common/cmake/rmw_security_commonConfig-version.cmake
ros_rmw_security_common-7.8.2.data/data/share/rmw_security_common/cmake/rmw_security_commonConfig.cmake
ros_rmw_security_common-7.8.2.data/data/share/rmw_security_common/cmake/rmw_security_common_libraryExport-release.cmake
ros_rmw_security_common-7.8.2.dist-info/METADATA
ros_rmw_security_common-7.8.2.dist-info/WHEEL
ros_rmw_security_common-7.8.2.dist-info/top_level.txt
ros_rmw_security_common-7.8.2.dist-info/RECORD
