Metadata-Version: 2.4
Name: ros-rmw-security-common
Version: 7.8.2
Summary: Wheel for the rmw_security_common (ros-rmw-security-common) ROS 2 package.
Requires-Dist: ros-rmw~=7.8.2
Requires-Dist: ros-rcutils~=6.9.8
Dynamic: description
Dynamic: description-content-type
Dynamic: requires-dist
Dynamic: summary
